{
  "site": "Hall Road",
  "records": [
	{
	  "date": "2020-12-22T12:00:00.000000-05:00",
	  "durationInSeconds": 900,
	  "zone": [
		[
		  [
			42.456211,
			-83.455702
		  ],
		  [
			42.456286,
			-83.455401
		  ],
		  [
			42.456060,
			-83.455127
		  ],
		  [
			42.455890,
			-83.455315
		  ],
		  [
			42.455906,
			-83.455836
		  ]
		],
		[
		  [
			42.454413,
			-83.459160
		  ],
		  [
			42.454255,
			-83.458542
		  ],
		  [
			42.453950,
			-83.458564
		  ],
		  [
			42.453930,
			-83.459557
		  ],
		  [
			42.454345,
			-83.460301
		  ]
		]
	  ]
	},
	{
	  "date": "2020-12-22T12:15:00.000000-05:00",
	  "durationInSeconds": 900,
	  "zone": [
		[
		  [
			42.456455,
			-83.455849
		  ],
		  [
			42.456602,
			-83.455355
		  ],
		  [
			42.456602,
			-83.455355
		  ],
		  [
			42.456232,
			-83.455175
		  ],
		  [
			42.456070,
			-83.455734
		  ]
		],
		[
		  [
			42.456098,
			-83.454195
		  ],
		  [
			42.455971,
			-83.454076
		  ],
		  [
			42.455741,
			-83.454215
		  ],
		  [
			42.455492,
			-83.454591
		  ],
		  [
			42.455583,
			-83.455026
		  ]
		]
	  ]
	},
	{
	  "date": "2020-12-22T12:30:00.000000-05:00",
	  "durationInSeconds": 900,
	  "zone": [
		[
		  [
			42.455026,
			-83.456056
		  ],
		  [
			42.454939,
			-83.456180
		  ],
		  [
			42.454698,
			-83.456528
		  ],
		  [
			42.454591,
			-83.456969
		  ],
		  [
			42.454653,
			-83.457542
		  ]
		],
		[
		  [
			42.453802,
			-83.460315
		  ],
		  [
			42.453727,
			-83.460492
		  ],
		  [
			42.453601,
			-83.460669
		  ],
		  [
			42.453636,
			-83.461179
		  ],
		  [
			42.453711,
			-83.461474
		  ]
		]
	  ]
	},
	{
	  "date": "2020-12-22T12:45:00.000000-05:00",
	  "durationInSeconds": 900,
	  "zone": [
		[
		  [
			42.457062,
			-83.457253
		  ],
		  [
			42.456935,
			-83.457338
		  ],
		  [
			42.456729,
			-83.457854
		  ],
		  [
			42.457204,
			-83.459035
		  ],
		  [
			42.458357,
			-83.460031
		  ]
		],
		[
		  [
			42.459124,
			-83.457403
		  ],
		  [
			42.459361,
			-83.456695
		  ],
		  [
			42.459171,
			-83.455943
		  ],
		  [
			42.458934,
			-83.456136
		  ],
		  [
			42.458759,
			-83.456802
		  ]
		]
	  ]
	}
  ]
}
